okap/__init__.py
okap/client.py
okap/errors.py
okap/models.py
okap/vault/__init__.py
okap/vault/storage.py
okap/vault/vault.py
okap-0.1.2.dist-info/METADATA
okap-0.1.2.dist-info/WHEEL
okap-0.1.2.dist-info/RECORD
