Metadata-Version: 2.4
Name: okap
Version: 0.1.2
Summary: Python SDK for OKAP (Open Key Access Protocol) - Secure API key delegation
Project-URL: Homepage, https://github.com/openkeyprotocol/python-sdk
Project-URL: Documentation, https://github.com/openkeyprotocol/okap
Project-URL: Repository, https://github.com/openkeyprotocol/python-sdk
Author-email: Hemanth HM <hemanth.hm@gmail.com>
License-Expression: MIT
Keywords: ai,anthropic,api-keys,oauth,okap,openai,security
Classifier: Development Status :: 3 - Alpha
Classifier: Intended Audience :: Developers
Classifier: License :: OSI Approved :: MIT License
Classifier: Programming Language :: Python :: 3
Classifier: Programming Language :: Python :: 3.10
Classifier: Programming Language :: Python :: 3.11
Classifier: Programming Language :: Python :: 3.12
Classifier: Programming Language :: Python :: 3.13
Requires-Python: >=3.10
Requires-Dist: httpx>=0.25.0
Requires-Dist: pydantic>=2.0.0
Provides-Extra: dev
Requires-Dist: mypy>=1.0.0; extra == 'dev'
Requires-Dist: pytest-asyncio>=0.21.0; extra == 'dev'
Requires-Dist: pytest>=7.0.0; extra == 'dev'
Requires-Dist: ruff>=0.1.0; extra == 'dev'
Provides-Extra: vault
Requires-Dist: fastapi>=0.100.0; extra == 'vault'
Requires-Dist: uvicorn>=0.23.0; extra == 'vault'
